py_metarium_decoder/__init__.py
py_metarium_decoder/base/__init__.py
py_metarium_decoder/base/decoder.py
py_metarium_decoder-0.0.1.41.dist-info/LICENSE
py_metarium_decoder-0.0.1.41.dist-info/METADATA
py_metarium_decoder-0.0.1.41.dist-info/WHEEL
py_metarium_decoder-0.0.1.41.dist-info/top_level.txt
py_metarium_decoder-0.0.1.41.dist-info/RECORD
