Metadata-Version: 2.1
Name: py-metarium-decoder
Version: 0.0.1.41
Summary: Python package for Metarium Decoder
Author: MetariumProject
Project-URL: Homepage, https://github.com/MetariumProject/py-metarium-decoder
Project-URL: Bug Tracker, https://github.com/MetariumProject/py-metarium-decoder/issues
Classifier: Programming Language :: Python :: 3
Classifier: License :: OSI Approved :: MIT License
Classifier: Operating System :: OS Independent
Requires-Python: >=3.9
License-File: LICENSE
Requires-Dist: py-metarium (==0.0.2.51)
Requires-Dist: substrate-interface (==1.4.0)
